{
  "scenario_name": "A5_edge_anomaly",
  "seed": 1001,
  "run_id": "20260608T091059_2f8284",
  "protocol": "mqtt",
  "architecture": "edge_filtered",
  "traffic_level": "peak",
  "num_spots": 500,
  "sim_duration_s": 10800.0,
  "heartbeat_interval_s": 900.0,
  "events_generated_total": 9624,
  "state_changes_generated_total": 3451,
  "heartbeats_generated_total": 6000,
  "initial_snapshots_generated_total": 0,
  "duplicate_sends_generated_total": 173,
  "frames_s2e_sent": 9624,
  "frames_s2e_delivered": 9119,
  "frames_s2e_dropped": 505,
  "bytes_s2e_sent": 184049,
  "bytes_s2e_received": 174316,
  "s2e_delivery_ratio": 0.9474,
  "proto_bytes_sent": 909739,
  "proto_retransmissions": 184,
  "proto_duplicate_deliveries": 92,
  "cloud_msgs_received": 4712,
  "unique_state_changes_applied_at_cloud": 3200,
  "duplicate_events_at_cloud": 0,
  "e2e_unique_delivery_ratio": 0.9273,
  "cloud_reflection_ratio": 0.978,
  "physical_delivery_ratio": 0.9299,
  "latency_mean_ms": 130.56,
  "latency_p50_ms": 111.32,
  "latency_p95_ms": 166.02,
  "latency_p99_ms": 1104.8,
  "latency_min_ms": 16.25,
  "latency_max_ms": 7079.03,
  "frames_e2c_sent": 4712,
  "frames_e2c_delivered": 4712,
  "frames_e2c_dropped": 0,
  "bytes_e2c_sent": 744141,
  "bytes_e2c_received": 744141,
  "backhaul_delivery_ratio": 1.0,
  "events_filtered_total": 4406,
  "events_forwarded_total": 4712,
  "aggregation_ratio": 1.0,
  "message_reduction_ratio": 0.4832,
  "heartbeats_suppressed": 4172,
  "heartbeats_forwarded": 1500,
  "quarantine_suppressed": 8,
  "anomalies_detected": 4410,
  "anomalies_resolved": 4271,
  "active_anomalies": 139,
  "adaptive_mode_switches": 0,
  "quarantined_spots_final": 105,
  "anomaly_detected_spots": 500,
  "fault_injected_count": 0
}