{
  "scenario_name": "E7_load_agg_low",
  "seed": 5001,
  "run_id": "20260627T214015_f8a79c",
  "protocol": "mqtt",
  "architecture": "edge_aggregated",
  "traffic_level": "low",
  "num_spots": 500,
  "sim_duration_s": 10800.0,
  "heartbeat_interval_s": 900.0,
  "events_generated_total": 6553,
  "state_changes_generated_total": 533,
  "heartbeats_generated_total": 6000,
  "initial_snapshots_generated_total": 0,
  "duplicate_sends_generated_total": 20,
  "frames_s2e_sent": 6553,
  "frames_s2e_delivered": 5809,
  "frames_s2e_dropped": 744,
  "frames_s2e_collisions": 396,
  "bytes_s2e_sent": 701924,
  "bytes_s2e_received": 622464,
  "s2e_delivery_ratio": 0.8865,
  "proto_bytes_sent": 245614,
  "proto_retransmissions": 36,
  "proto_duplicate_deliveries": 18,
  "cloud_batches_received": 571,
  "cloud_events_pre_dedup": 2001,
  "cloud_events_post_dedup": 1950,
  "cloud_msgs_received": 2001,
  "unique_state_changes_applied_at_cloud": 450,
  "duplicate_events_at_cloud": 51,
  "e2e_unique_delivery_ratio": 0.8443,
  "cloud_reflection_ratio": 0.98,
  "physical_delivery_ratio": 0.8608,
  "latency_mean_ms": 7651.63,
  "latency_p50_ms": 7631.91,
  "latency_p95_ms": 14231.0,
  "latency_p99_ms": 14977.44,
  "latency_min_ms": 308.32,
  "latency_max_ms": 15116.07,
  "frames_e2c_sent": 554,
  "frames_e2c_delivered": 553,
  "frames_e2c_dropped": 0,
  "bytes_e2c_sent": 192115,
  "bytes_e2c_received": 191821,
  "backhaul_delivery_ratio": 1.0,
  "events_filtered_total": 3856,
  "events_forwarded_total": 1953,
  "aggregation_ratio": 0.2837,
  "message_reduction_ratio": 0.9046,
  "events_per_cloud_message": 3.53,
  "heartbeats_suppressed": 3843,
  "heartbeats_forwarded": 1488,
  "quarantine_suppressed": 0,
  "anomalies_detected": 0,
  "anomalies_resolved": 0,
  "active_anomalies": 0,
  "adaptive_mode_switches": 0,
  "adaptive_window_adjustments": 0,
  "adaptive_min_window_dr": null,
  "quarantined_spots_final": 0,
  "anomaly_detected_spots": 0,
  "fault_injected_count": 0,
  "fault_true_count": 0,
  "anomaly_precision": null,
  "anomaly_recall": null,
  "anomaly_f1": null
}